packagesj/__init__.py
UCS633_topsis_SumitJain-2.0.1.dist-info/LICENSE.txt
UCS633_topsis_SumitJain-2.0.1.dist-info/METADATA
UCS633_topsis_SumitJain-2.0.1.dist-info/WHEEL
UCS633_topsis_SumitJain-2.0.1.dist-info/entry_points.txt
UCS633_topsis_SumitJain-2.0.1.dist-info/top_level.txt
UCS633_topsis_SumitJain-2.0.1.dist-info/RECORD
