Metadata-Version: 2.1
Name: UCS633-topsis-SumitJain
Version: 2.0.1
Summary: A python package to implement topsis(MCDM)
Home-page: https://github.com/SumitJain01/MyProjects
Author: Sumit Jain
Author-email: sumitjaini1998@gmail.com
License: UNKNOWN
Platform: UNKNOWN
Classifier: Programming Language :: Python :: 3
Classifier: Programming Language :: Python :: 3.7
Classifier: License :: OSI Approved :: MIT License
Classifier: Operating System :: OS Independent
Requires-Python: >=3.6
Requires-Dist: pandas
Requires-Dist: numpy
Requires-Dist: scipy
